dag_cost_tracker/__init__.py
dag_cost_tracker/cli.py
dag_cost_tracker/config.py
dag_cost_tracker/cost_calculator.py
dag_cost_tracker/db.py
dag_cost_tracker/listener.py
dag_cost_tracker/models.py
dag_cost_tracker/plugin.py
dag_cost_tracker-0.1.3.dist-info/licenses/LICENSE
dag_cost_tracker-0.1.3.dist-info/METADATA
dag_cost_tracker-0.1.3.dist-info/WHEEL
dag_cost_tracker-0.1.3.dist-info/entry_points.txt
dag_cost_tracker-0.1.3.dist-info/top_level.txt
dag_cost_tracker-0.1.3.dist-info/RECORD
