Metadata-Version: 2.4
Name: dag-cost-tracker
Version: 0.1.3
Summary: A DAG cost tracking plugin for Apache Airflow
Home-page: https://github.com/azmatsiddique/dag-cost-tracker
Author: Azmat Siddique
License: MIT
Project-URL: Bug Tracker, https://github.com/azmatsiddique/dag-cost-tracker/issues
Project-URL: Source Code, https://github.com/azmatsiddique/dag-cost-tracker
Classifier: Development Status :: 4 - Beta
Classifier: Environment :: Plugins
Classifier: Intended Audience :: Developers
Classifier: Intended Audience :: System Administrators
Classifier: License :: OSI Approved :: MIT License
Classifier: Programming Language :: Python :: 3
Classifier: Programming Language :: Python :: 3.8
Classifier: Programming Language :: Python :: 3.9
Classifier: Programming Language :: Python :: 3.10
Classifier: Programming Language :: Python :: 3.11
Classifier: Topic :: System :: Monitoring
Requires-Python: >=3.8
License-File: LICENSE
Requires-Dist: apache-airflow>=2.0.0
Requires-Dist: SQLAlchemy<2.0.0,>=1.3.0
Requires-Dist: PyYAML>=5.1
Requires-Dist: click>=7.0
Requires-Dist: tabulate>=0.8.0
Dynamic: author
Dynamic: classifier
Dynamic: description
Dynamic: description-content-type
Dynamic: home-page
Dynamic: license
Dynamic: license-file
Dynamic: project-url
Dynamic: requires-dist
Dynamic: requires-python
Dynamic: summary
